fancy_signatures/__init__.py
fancy_signatures/__version__.py
fancy_signatures/alias.py
fancy_signatures/api.py
fancy_signatures/exceptions.py
fancy_signatures/settings.py
fancy_signatures/core/__init__.py
fancy_signatures/core/empty.py
fancy_signatures/core/field.py
fancy_signatures/core/interface.py
fancy_signatures/default/__init__.py
fancy_signatures/default/defaults.py
fancy_signatures/typecasting/__handler_lib.py
fancy_signatures/typecasting/__init__.py
fancy_signatures/typecasting/default.py
fancy_signatures/typecasting/factory.py
fancy_signatures/typecasting/generic_alias.py
fancy_signatures/typecasting/handlers.py
fancy_signatures/typecasting/special_origins.py
fancy_signatures/typecasting/union.py
fancy_signatures/validation/__init__.py
fancy_signatures/validation/mixins.py
fancy_signatures/validation/validators.py
fancy_signatures/validation/related/__init__.py
fancy_signatures/validation/related/related.py
fancy_signatures/validation/related/validators.py
FancySignatures-0.1.2.dist-info/LICENSE
FancySignatures-0.1.2.dist-info/METADATA
FancySignatures-0.1.2.dist-info/WHEEL
FancySignatures-0.1.2.dist-info/top_level.txt
FancySignatures-0.1.2.dist-info/RECORD
