Metadata-Version: 2.1
Name: FancySignatures
Version: 0.1.2
Summary: Package to leverage standard type hints in function and method signatures.
Author-email: Joep Atol <joep.atol@live.nl>
Project-URL: Homepage, https://github.com/joepatol/FancySignatures
Project-URL: Bug Tracker, https://github.com/joepatol/FancySignatures/issues
Project-URL: Documentation, https://joepatol.github.io/FancySignatures/
Classifier: Programming Language :: Python :: 3
Classifier: Operating System :: OS Independent
Classifier: License :: OSI Approved :: Apache Software License
Requires-Python: >=3.10
License-File: LICENSE
Requires-Dist: typing-extensions >=4.7.1
